nmmd/__init__.py
nmmd/base.py
nmmd/ext/__init__.py
nmmd/ext/regex.py
nmmd-0.0.3.dist-info/RECORD
nmmd-0.0.3.dist-info/METADATA
nmmd-0.0.3.dist-info/metadata.json
nmmd-0.0.3.dist-info/WHEEL
nmmd-0.0.3.dist-info/DESCRIPTION.rst
nmmd-0.0.3.dist-info/top_level.txt
